{
  "keys": {
    "__APP_NAME__": "Name of the application/microservice",
    "__IMAGE_REPO__": "Container image repository (e.g., docker.io/myorg/myapp)",
    "__SERVICE_PORT__": "Port the application listens on",
    "__NAMESPACE_DEV__": "Kubernetes namespace for dev environment",
    "__NAMESPACE_STAGING__": "Kubernetes namespace for staging environment",
    "__NAMESPACE_PROD__": "Kubernetes namespace for prod environment",
    "__REPLICAS_DEV__": "Number of replicas in dev",
    "__REPLICAS_STAGING__": "Number of replicas in staging",
    "__REPLICAS_PROD__": "Number of replicas in prod",
    "__IMAGE_TAG_DEV__": "Image tag for dev (e.g., latest)",
    "__IMAGE_TAG_STAGING__": "Image tag for staging",
    "__IMAGE_TAG_PROD__": "Image tag for prod",
    "__INGRESS_ENABLED_DEV__": "true/false for ingress in dev",
    "__INGRESS_ENABLED_STAGING__": "true/false for ingress in staging",
    "__INGRESS_ENABLED_PROD__": "true/false for ingress in prod",
    "__INGRESS_HOST_DEV__": "Ingress hostname for dev",
    "__INGRESS_HOST_STAGING__": "Ingress hostname for staging",
    "__INGRESS_HOST_PROD__": "Ingress hostname for prod",
    "__CPU_LIMIT_DEV__": "CPU limit for dev (e.g., 500m)",
    "__CPU_LIMIT_STAGING__": "CPU limit for staging",
    "__CPU_LIMIT_PROD__": "CPU limit for prod",
    "__MEMORY_LIMIT_DEV__": "Memory limit for dev (e.g., 256Mi)",
    "__MEMORY_LIMIT_STAGING__": "Memory limit for staging",
    "__MEMORY_LIMIT_PROD__": "Memory limit for prod",
    "__CPU_REQUEST_DEV__": "CPU request for dev",
    "__CPU_REQUEST_STAGING__": "CPU request for staging",
    "__CPU_REQUEST_PROD__": "CPU request for prod",
    "__MEMORY_REQUEST_DEV__": "Memory request for dev",
    "__MEMORY_REQUEST_STAGING__": "Memory request for staging",
    "__MEMORY_REQUEST_PROD__": "Memory request for prod"
  }
}
